gmi_ieops/__init__.py
gmi_ieops/version.py
gmi_ieops/config/__init__.py
gmi_ieops/config/env.py
gmi_ieops/handler/__init__.py
gmi_ieops/handler/client.py
gmi_ieops/handler/engine.py
gmi_ieops/handler/handler.py
gmi_ieops/handler/interceptor.py
gmi_ieops/handler/register.py
gmi_ieops/handler/router.py
gmi_ieops/handler/server.py
gmi_ieops/handler/tokenizer.py
gmi_ieops/storage/__init__.py
gmi_ieops/storage/filesystem.py
gmi_ieops/storage/nfs.py
gmi_ieops/storage/webdav.py
gmi_ieops/utils/__init__.py
gmi_ieops/utils/file.py
gmi_ieops/utils/llm_sampling_params.py
gmi_ieops/utils/log.py
gmi_ieops/utils/queue.py
gmi_ieops/utils/signal.py
gmi_ieops/utils/subprocess_manager.py
gmi_ieops/utils/util.py
gmi_ieops-0.4.3.dist-info/METADATA
gmi_ieops-0.4.3.dist-info/WHEEL
gmi_ieops-0.4.3.dist-info/top_level.txt
gmi_ieops-0.4.3.dist-info/RECORD
