Metadata-Version: 2.4
Name: gmi_ieops
Version: 0.4.3
Author: GMICloud Inc.
Requires-Python: >=3.10
Requires-Dist: fastapi
Requires-Dist: uvicorn
Requires-Dist: aiohttp
Requires-Dist: loguru
Requires-Dist: requests
Requires-Dist: requests-unixsocket
Requires-Dist: typing_extensions
Requires-Dist: webdavclient3
Requires-Dist: certifi
Requires-Dist: click!=8.3.*,>=7.0
Dynamic: author
Dynamic: requires-dist
Dynamic: requires-python
